enerdata/__init__.py
enerdata/calendars/__init__.py
enerdata/contracts/__init__.py
enerdata/contracts/contract.py
enerdata/contracts/normalized_power.py
enerdata/contracts/tariff.py
enerdata/cups/__init__.py
enerdata/cups/cups.py
enerdata/datetime/__init__.py
enerdata/datetime/holidays.py
enerdata/datetime/solar_hour.py
enerdata/datetime/station.py
enerdata/datetime/timezone.py
enerdata/datetime/work_and_holidays.py
enerdata/metering/__init__.py
enerdata/metering/measure.py
enerdata/metering/meter.py
enerdata/profiles/__init__.py
enerdata/profiles/profile.py
enerdata/profiles/data/coefficients_HIDRO_RE.csv
enerdata/profiles/data/coefficients_RE.xlsx
spec/__init__.py
enerdata-0.24.0rc2.dist-info/LICENSE
enerdata-0.24.0rc2.dist-info/METADATA
enerdata-0.24.0rc2.dist-info/WHEEL
enerdata-0.24.0rc2.dist-info/top_level.txt
enerdata-0.24.0rc2.dist-info/RECORD
