Metadata-Version: 2.1
Name: enerdata
Version: 0.24.0rc2
Summary: A set of energy models
Home-page: http://code.gisce.net
Author: GISCE-TI, S.L.
Author-email: devel@gisce.net
License: MIT
Platform: UNKNOWN
Requires-Dist: pytz
Requires-Dist: workalendar (<8.0.0)
